{"Country":"United States","GDP_USD_Billion":26949.64}
{"Country":"China","GDP_USD_Billion":17700.9}
{"Country":"Germany","GDP_USD_Billion":4429.84}
{"Country":"Japan","GDP_USD_Billion":4230.86}
{"Country":"India","GDP_USD_Billion":3732.22}
{"Country":"United Kingdom","GDP_USD_Billion":3332.06}
{"Country":"France","GDP_USD_Billion":3049.02}
{"Country":"Italy","GDP_USD_Billion":2186.08}
{"Country":"Brazil","GDP_USD_Billion":2126.81}
{"Country":"Canada","GDP_USD_Billion":2117.8}
{"Country":"Russia","GDP_USD_Billion":1862.47}
{"Country":"Mexico","GDP_USD_Billion":1811.47}
{"Country":"South Korea","GDP_USD_Billion":1709.23}
{"Country":"Australia","GDP_USD_Billion":1687.71}
{"Country":"Spain","GDP_USD_Billion":1582.05}
{"Country":"Indonesia","GDP_USD_Billion":1417.39}
{"Country":"Turkey","GDP_USD_Billion":1154.6}
{"Country":"Netherlands","GDP_USD_Billion":1092.75}
{"Country":"Saudi Arabia","GDP_USD_Billion":1069.44}
{"Country":"Switzerland","GDP_USD_Billion":905.68}
{"Country":"Poland","GDP_USD_Billion":842.17}
{"Country":"Taiwan","GDP_USD_Billion":751.93}
{"Country":"Belgium","GDP_USD_Billion":627.51}
{"Country":"Argentina","GDP_USD_Billion":621.83}
{"Country":"Sweden","GDP_USD_Billion":597.11}
{"Country":"Ireland","GDP_USD_Billion":589.57}
{"Country":"Norway","GDP_USD_Billion":546.77}
{"Country":"Austria","GDP_USD_Billion":526.18}
{"Country":"Israel","GDP_USD_Billion":521.69}
{"Country":"Thailand","GDP_USD_Billion":512.19}
{"Country":"United Arab Emirates","GDP_USD_Billion":509.18}
{"Country":"Singapore","GDP_USD_Billion":497.35}
{"Country":"Bangladesh","GDP_USD_Billion":446.35}
{"Country":"Philippines","GDP_USD_Billion":435.68}
{"Country":"Vietnam","GDP_USD_Billion":433.36}
{"Country":"Malaysia","GDP_USD_Billion":430.89}
{"Country":"Denmark","GDP_USD_Billion":420.8}
{"Country":"Egypt","GDP_USD_Billion":398.4}
{"Country":"Nigeria","GDP_USD_Billion":390.0}
{"Country":"Hong Kong","GDP_USD_Billion":385.55}
{"Country":"South Africa","GDP_USD_Billion":380.91}
{"Country":"Iran","GDP_USD_Billion":366.44}
{"Country":"Colombia","GDP_USD_Billion":363.83}
{"Country":"Romania","GDP_USD_Billion":350.41}
{"Country":"Chile","GDP_USD_Billion":344.4}
{"Country":"Pakistan","GDP_USD_Billion":340.64}
{"Country":"Czech Republic","GDP_USD_Billion":335.24}
{"Country":"Finland","GDP_USD_Billion":305.69}
{"Country":"Iraq","GDP_USD_Billion":297.69}
{"Country":"Portugal","GDP_USD_Billion":276.43}
{"Country":"Peru","GDP_USD_Billion":264.64}
{"Country":"Kazakhstan","GDP_USD_Billion":259.29}
{"Country":"New Zealand","GDP_USD_Billion":249.41}
{"Country":"Greece","GDP_USD_Billion":242.38}
{"Country":"Qatar","GDP_USD_Billion":235.5}
{"Country":"Algeria","GDP_USD_Billion":224.11}
{"Country":"Hungary","GDP_USD_Billion":203.83}
{"Country":"Ukraine","GDP_USD_Billion":173.41}
{"Country":"Kuwait","GDP_USD_Billion":159.69}
{"Country":"Ethiopia","GDP_USD_Billion":155.8}
{"Country":"Morocco","GDP_USD_Billion":147.34}
{"Country":"Slovakia","GDP_USD_Billion":133.04}
{"Country":"Cuba","GDP_USD_Billion":null}
{"Country":"Dominican Republic","GDP_USD_Billion":120.63}
{"Country":"Ecuador","GDP_USD_Billion":118.69}
{"Country":"Puerto Rico","GDP_USD_Billion":117.52}
{"Country":"Kenya","GDP_USD_Billion":112.75}
{"Country":"Oman","GDP_USD_Billion":108.28}
{"Country":"Bulgaria","GDP_USD_Billion":103.1}
{"Country":"Guatemala","GDP_USD_Billion":102.77}
{"Country":"Angola","GDP_USD_Billion":93.8}
{"Country":"Venezuela","GDP_USD_Billion":92.21}
{"Country":"Uzbekistan","GDP_USD_Billion":90.39}
{"Country":"Luxembourg","GDP_USD_Billion":89.09}
{"Country":"Costa Rica","GDP_USD_Billion":85.59}
{"Country":"Tanzania","GDP_USD_Billion":84.03}
{"Country":"Panama","GDP_USD_Billion":82.35}
{"Country":"Turkmenistan","GDP_USD_Billion":81.82}
{"Country":"Croatia","GDP_USD_Billion":80.19}
{"Country":"Ivory Coast","GDP_USD_Billion":79.43}
{"Country":"Lithuania","GDP_USD_Billion":79.43}
{"Country":"Azerbaijan","GDP_USD_Billion":77.39}
{"Country":"Ghana","GDP_USD_Billion":76.63}
{"Country":"Uruguay","GDP_USD_Billion":76.24}
{"Country":"Serbia","GDP_USD_Billion":75.02}
{"Country":"Myanmar","GDP_USD_Billion":74.86}
{"Country":"Sri Lanka","GDP_USD_Billion":null}
{"Country":"Belarus","GDP_USD_Billion":68.86}
{"Country":"Slovenia","GDP_USD_Billion":68.39}
{"Country":"DR Congo","GDP_USD_Billion":67.51}
{"Country":"Uganda","GDP_USD_Billion":52.39}
{"Country":"Tunisia","GDP_USD_Billion":51.27}
{"Country":"Jordan","GDP_USD_Billion":50.02}
{"Country":"Cameroon","GDP_USD_Billion":49.26}
{"Country":"Bolivia","GDP_USD_Billion":46.8}
{"Country":"Latvia","GDP_USD_Billion":46.67}
{"Country":"Bahrain","GDP_USD_Billion":44.99}
{"Country":"Paraguay","GDP_USD_Billion":44.14}
{"Country":"Estonia","GDP_USD_Billion":41.8}
{"Country":"Nepal","GDP_USD_Billion":41.34}
{"Country":"Libya","GDP_USD_Billion":40.19}
{"Country":"Macau","GDP_USD_Billion":38.48}
{"Country":"Lebanon","GDP_USD_Billion":null}
{"Country":"El Salvador","GDP_USD_Billion":35.34}
{"Country":"Honduras","GDP_USD_Billion":33.99}
{"Country":"Zimbabwe","GDP_USD_Billion":32.42}
{"Country":"Cyprus","GDP_USD_Billion":32.03}
{"Country":"Papua New Guinea","GDP_USD_Billion":31.69}
{"Country":"Senegal","GDP_USD_Billion":31.14}
{"Country":"Cambodia","GDP_USD_Billion":30.94}
{"Country":"Iceland","GDP_USD_Billion":30.57}
{"Country":"Georgia","GDP_USD_Billion":30.02}
{"Country":"Zambia","GDP_USD_Billion":29.54}
{"Country":"Trinidad and Tobago","GDP_USD_Billion":27.89}
{"Country":"Bosnia and Herzegovina","GDP_USD_Billion":26.95}
{"Country":"Haiti","GDP_USD_Billion":25.99}
{"Country":"Sudan","GDP_USD_Billion":25.57}
{"Country":"Armenia","GDP_USD_Billion":24.54}
{"Country":"Guinea","GDP_USD_Billion":23.2}
{"Country":"Albania","GDP_USD_Billion":23.03}
{"Country":"Mozambique","GDP_USD_Billion":21.94}
{"Country":"Mali","GDP_USD_Billion":21.31}
{"Country":"Yemen","GDP_USD_Billion":21.05}
{"Country":"Burkina Faso","GDP_USD_Billion":20.79}
{"Country":"Botswana","GDP_USD_Billion":20.76}
{"Country":"Malta","GDP_USD_Billion":20.31}
{"Country":"Benin","GDP_USD_Billion":19.94}
{"Country":"Syria","GDP_USD_Billion":null}
{"Country":"Gabon","GDP_USD_Billion":19.32}
{"Country":"Palestine","GDP_USD_Billion":18.11}
{"Country":"Mongolia","GDP_USD_Billion":18.78}
{"Country":"Jamaica","GDP_USD_Billion":18.76}
{"Country":"Nicaragua","GDP_USD_Billion":17.35}
{"Country":"Niger","GDP_USD_Billion":17.07}
{"Country":"North Korea","GDP_USD_Billion":null}
{"Country":"Guyana","GDP_USD_Billion":16.33}
{"Country":"Moldova","GDP_USD_Billion":16.0}
{"Country":"North Macedonia","GDP_USD_Billion":15.8}
{"Country":"Madagascar","GDP_USD_Billion":15.76}
{"Country":"Brunei","GDP_USD_Billion":15.15}
{"Country":"Afghanistan","GDP_USD_Billion":null}
{"Country":"Mauritius","GDP_USD_Billion":14.82}
{"Country":"Congo","GDP_USD_Billion":14.41}
{"Country":"Laos","GDP_USD_Billion":14.24}
{"Country":"Rwanda","GDP_USD_Billion":13.93}
{"Country":"Bahamas","GDP_USD_Billion":13.88}
{"Country":"Malawi","GDP_USD_Billion":13.18}
{"Country":"Kyrgyzstan","GDP_USD_Billion":12.68}
{"Country":"Namibia","GDP_USD_Billion":12.65}
{"Country":"Chad","GDP_USD_Billion":12.6}
{"Country":"Tajikistan","GDP_USD_Billion":11.82}
{"Country":"Somalia","GDP_USD_Billion":11.52}
{"Country":"Kosovo","GDP_USD_Billion":10.47}
{"Country":"Mauritania","GDP_USD_Billion":10.36}
{"Country":"New Caledonia","GDP_USD_Billion":null}
{"Country":"Equatorial Guinea","GDP_USD_Billion":10.04}
{"Country":"Togo","GDP_USD_Billion":9.11}
{"Country":"Monaco","GDP_USD_Billion":null}
{"Country":"Bermuda","GDP_USD_Billion":null}
{"Country":"Montenegro","GDP_USD_Billion":7.06}
{"Country":"Maldives","GDP_USD_Billion":6.98}
{"Country":"Liechtenstein","GDP_USD_Billion":null}
{"Country":"South Sudan","GDP_USD_Billion":6.27}
{"Country":"Barbados","GDP_USD_Billion":6.22}
{"Country":"French Polynesia","GDP_USD_Billion":null}
{"Country":"Cayman Islands","GDP_USD_Billion":null}
{"Country":"Fiji","GDP_USD_Billion":5.51}
{"Country":"Eswatini","GDP_USD_Billion":4.65}
{"Country":"Liberia","GDP_USD_Billion":4.35}
{"Country":"Djibouti","GDP_USD_Billion":3.87}
{"Country":"Aruba","GDP_USD_Billion":3.83}
{"Country":"Andorra","GDP_USD_Billion":3.69}
{"Country":"Suriname","GDP_USD_Billion":3.54}
{"Country":"Sierra Leone","GDP_USD_Billion":3.52}
{"Country":"Greenland","GDP_USD_Billion":null}
{"Country":"Belize","GDP_USD_Billion":3.22}
{"Country":"Burundi","GDP_USD_Billion":3.19}
{"Country":"Central African Republic","GDP_USD_Billion":2.76}
{"Country":"Cura\u00e7ao","GDP_USD_Billion":null}
{"Country":"Bhutan","GDP_USD_Billion":2.69}
{"Country":"Cape Verde","GDP_USD_Billion":2.6}
{"Country":"Saint Lucia","GDP_USD_Billion":2.47}
{"Country":"Gambia","GDP_USD_Billion":2.39}
{"Country":"Lesotho","GDP_USD_Billion":2.37}
{"Country":"Eritrea","GDP_USD_Billion":null}
{"Country":"Seychelles","GDP_USD_Billion":2.08}
{"Country":"Zanzibar","GDP_USD_Billion":null}
{"Country":"East Timor","GDP_USD_Billion":2.02}
{"Country":"San Marino","GDP_USD_Billion":2.0}
{"Country":"Guinea-Bissau","GDP_USD_Billion":1.99}
{"Country":"Antigua and Barbuda","GDP_USD_Billion":1.95}
{"Country":"Solomon Islands","GDP_USD_Billion":1.69}
{"Country":"Sint Maarten","GDP_USD_Billion":null}
{"Country":"British Virgin Islands","GDP_USD_Billion":null}
{"Country":"Comoros","GDP_USD_Billion":1.36}
{"Country":"Grenada","GDP_USD_Billion":1.31}
{"Country":"Vanuatu","GDP_USD_Billion":1.17}
{"Country":"Turks and Caicos Islands","GDP_USD_Billion":null}
{"Country":"Saint Kitts and Nevis","GDP_USD_Billion":1.07}
{"Country":"Saint Vincent and the Grenadines","GDP_USD_Billion":1.04}
{"Country":"Samoa","GDP_USD_Billion":0.94}
{"Country":"Dominica","GDP_USD_Billion":0.7}
{"Country":"S\u00e3o Tom\u00e9 and Pr\u00edncipe","GDP_USD_Billion":0.67}
{"Country":"Tonga","GDP_USD_Billion":0.55}
{"Country":"Micronesia","GDP_USD_Billion":0.46}
{"Country":"Cook Islands","GDP_USD_Billion":null}
{"Country":"Anguilla","GDP_USD_Billion":null}
{"Country":"Marshall Islands","GDP_USD_Billion":0.28}
{"Country":"Palau","GDP_USD_Billion":0.27}
{"Country":"Kiribati","GDP_USD_Billion":0.25}
{"Country":"Nauru","GDP_USD_Billion":0.15}
{"Country":"Montserrat","GDP_USD_Billion":null}
{"Country":"Tuvalu","GDP_USD_Billion":0.06}
